brs_xss-2.1.1.dist-info/licenses/LICENSE
brsxss/__init__.py
brsxss/version.py
brsxss/core/__init__.py
brsxss/core/advanced_waf_evasion.py
brsxss/core/basic_headers_analyzer.py
brsxss/core/blind_xss.py
brsxss/core/confidence_calculator.py
brsxss/core/config_manager.py
brsxss/core/context.py
brsxss/core/context_analyzer.py
brsxss/core/context_calculator.py
brsxss/core/context_payloads.py
brsxss/core/context_types.py
brsxss/core/cors_analyzer.py
brsxss/core/csp_analyzer.py
brsxss/core/css_context_detector.py
brsxss/core/encoding_evasions.py
brsxss/core/evasion_techniques.py
brsxss/core/evasion_types.py
brsxss/core/exploitability_calculator.py
brsxss/core/filter_detector.py
brsxss/core/header_scorer.py
brsxss/core/header_types.py
brsxss/core/html_context_detector.py
brsxss/core/http_client.py
brsxss/core/impact_calculator.py
brsxss/core/javascript_context_detector.py
brsxss/core/metadata_collector.py
brsxss/core/metadata_exporter.py
brsxss/core/metadata_types.py
brsxss/core/ml_integration.py
brsxss/core/payload_generator.py
brsxss/core/payload_types.py
brsxss/core/payloads.py
brsxss/core/polyglot_generator.py
brsxss/core/reflection.py
brsxss/core/reflection_analyzer.py
brsxss/core/reflection_detector.py
brsxss/core/reflection_types.py
brsxss/core/request_auto_detector.py
brsxss/core/request_builder.py
brsxss/core/request_types.py
brsxss/core/risk_analyzer.py
brsxss/core/scan_metadata.py
brsxss/core/scanner.py
brsxss/core/scoring.py
brsxss/core/scoring_engine.py
brsxss/core/scoring_types.py
brsxss/core/security_headers.py
brsxss/core/similarity_matcher.py
brsxss/core/waf_evasions.py
brsxss/core/waf_specific_evasions.py
brsxss/crawler/__init__.py
brsxss/crawler/data_models.py
brsxss/crawler/engine.py
brsxss/crawler/extracted_form.py
brsxss/crawler/form_extractor.py
brsxss/crawler/form_field_types.py
brsxss/crawler/form_parser.py
brsxss/crawler/scope.py
brsxss/crawler/url_discovery.py
brsxss/dom/__init__.py
brsxss/dom/ast_extractor.py
brsxss/dom/ast_types.py
brsxss/dom/data_flow_analyzer.py
brs_xss-2.1.1.dist-info/METADATA
brs_xss-2.1.1.dist-info/WHEEL
brs_xss-2.1.1.dist-info/entry_points.txt
brs_xss-2.1.1.dist-info/top_level.txt
brs_xss-2.1.1.dist-info/RECORD
