Metadata-Version: 2.4
Name: brs-xss
Version: 2.1.1
Summary: Context-aware async XSS scanner for CI/CD
Author: Brabus
License: MIT
Project-URL: Homepage, https://github.com/EPTLLC/brs-xss
Project-URL: Documentation, https://github.com/EPTLLC/brs-xss/wiki
Project-URL: Issues, https://github.com/EPTLLC/brs-xss/issues
Project-URL: Changelog, https://github.com/EPTLLC/brs-xss/releases
Keywords: security,xss,dast,sarif,playwright,bug-bounty,ci-cd,async,context-aware
Classifier: License :: OSI Approved :: MIT License
Classifier: Programming Language :: Python :: 3
Classifier: Programming Language :: Python :: 3 :: Only
Classifier: Programming Language :: Python :: 3.8
Classifier: Programming Language :: Python :: 3.9
Classifier: Programming Language :: Python :: 3.10
Classifier: Programming Language :: Python :: 3.11
Classifier: Programming Language :: Python :: 3.12
Classifier: Operating System :: OS Independent
Classifier: Topic :: Security
Classifier: Topic :: Security :: Cryptography
Classifier: Intended Audience :: Developers
Classifier: Intended Audience :: Information Technology
Classifier: Intended Audience :: System Administrators
Classifier: Development Status :: 5 - Production/Stable
Classifier: Environment :: Console
Requires-Python: >=3.8
License-File: LICENSE
Requires-Dist: aiohttp<4.0,>=3.8
Requires-Dist: typer<0.11,>=0.9
Requires-Dist: rich<14.0,>=13.0
Requires-Dist: pyyaml<7.0,>=6.0
Requires-Dist: jinja2<4.0,>=3.1
Requires-Dist: babel<3.0,>=2.12
Requires-Dist: polib<2.0,>=1.2
Requires-Dist: playwright<1.60.0,>=1.40.0
Requires-Dist: beautifulsoup4<4.13,>=4.12.3
Provides-Extra: dev
Requires-Dist: pytest<9,>=8; extra == "dev"
Requires-Dist: pytest-cov<5,>=4; extra == "dev"
Requires-Dist: pytest-asyncio<0.24,>=0.23; extra == "dev"
Requires-Dist: aresponses<4,>=3; extra == "dev"
Requires-Dist: pyfakefs<6,>=5; extra == "dev"
Dynamic: license-file
